farsight/.DS_Store
farsight/__init__.py
farsight/base.html
farsight/farsight.js
farsight/farsight.py
farsight/version.txt
farsight/__pycache__/__init__.cpython-37.pyc
farsight/__pycache__/__init__.cpython-39.pyc
farsight/__pycache__/farsight.cpython-39.pyc
farsight/__pycache__/timbertrek.cpython-37.pyc
farsight/__pycache__/timbertrek.cpython-39.pyc
farsight/__pycache__/wizmap.cpython-39.pyc
farsight-0.1.6.dist-info/METADATA
farsight-0.1.6.dist-info/WHEEL
farsight-0.1.6.dist-info/top_level.txt
farsight-0.1.6.dist-info/RECORD
